AUTHORS
ChangeLog
LICENSE
README.md
beka.yaml
bird.conf
bird6.conf
birdc.sh
birdc6.sh
codecheck-requirements.txt
daemon.json
deploy_bird.sh
deploy_test.sh
requirements.txt
run.py
run_tests.sh
setup.cfg
setup.py
test-requirements.txt
.github/dependabot.yml
.github/workflows/release-python.yml
.github/workflows/tests-codecheck.yml
.github/workflows/tests-unit.yml
.github/workflows/tests-yaml-lint.yml
.github/workflows/disabled/release-debian.yml
beka/__init__.py
beka/beka.py
beka/bgp_message.py
beka/chopper.py
beka/error.py
beka/event.py
beka/ip.py
beka/packing_tools.py
beka/peering.py
beka/route.py
beka/state_machine.py
beka/stream_server.py
beka/timer.py
c65beka.egg-info/PKG-INFO
c65beka.egg-info/SOURCES.txt
c65beka.egg-info/dependency_links.txt
c65beka.egg-info/not-zip-safe
c65beka.egg-info/pbr.json
c65beka.egg-info/requires.txt
c65beka.egg-info/top_level.txt
debian/README.source
debian/changelog
debian/compat
debian/control
debian/copyright
debian/rules
debian/source/format
test/codecheck/min_pylint.sh
test/codecheck/pylint.sh
test/codecheck/src_files.sh
test/unit/test_beka.py
test/unit/test_bgp_message.py
test/unit/test_chopper.py
test/unit/test_ip.py
test/unit/test_peering.py
test/unit/test_state_machine.py
test/unit/test_timer.py