Metadata-Version: 2.1
Name: c65beka
Version: 1.0.2
Summary: A bare-bones BGP speaker
Home-page: https://github.com/c65sdn/beka
Author: Sam Russell
Author-email: sam.h.russell@gmail.com
License: Apache-2
Keywords: bgp,beka,routing,sdn,networking
Classifier: Development Status :: 2 - Pre-Alpha
Classifier: Intended Audience :: System Administrators
Classifier: License :: OSI Approved :: Apache Software License
Classifier: Programming Language :: Python :: 3
Requires-Python: >=3.8
License-File: LICENSE
License-File: AUTHORS
